<?xml version="1.0" encoding="UTF-8"?>
<MetaDataObject xmlns="http://v8.1c.ru/8.3/MDClasses" xmlns:app="http://v8.1c.ru/8.2/managed-application/core" xmlns:cfg="http://v8.1c.ru/8.1/data/enterprise/current-config" xmlns:cmi="http://v8.1c.ru/8.2/managed-application/cmi" xmlns:ent="http://v8.1c.ru/8.1/data/enterprise" xmlns:lf="http://v8.1c.ru/8.2/managed-application/logform" xmlns:style="http://v8.1c.ru/8.1/data/ui/style" xmlns:sys="http://v8.1c.ru/8.1/data/ui/fonts/system" xmlns:v8="http://v8.1c.ru/8.1/data/core" xmlns:v8ui="http://v8.1c.ru/8.1/data/ui" xmlns:web="http://v8.1c.ru/8.1/data/ui/colors/web" xmlns:win="http://v8.1c.ru/8.1/data/ui/colors/windows" xmlns:xen="http://v8.1c.ru/8.3/xcf/enums" xmlns:xpr="http://v8.1c.ru/8.3/xcf/predef" xmlns:xr="http://v8.1c.ru/8.3/xcf/readable" xmlns:xs="http://www.w3.org/2001/XMLSchema" xmlns:xsi="http://www.w3.org/2001/XMLSchema-instance" version="2.1">
	<Constant uuid="1f1096b5-b3a8-4af2-af89-bcd53e0a3dcd">
		<InternalInfo>
			<xr:GeneratedType name="ConstantManager.SupportServiceSoftwareInterfaceAddress" category="Manager">
				<xr:TypeId>a7ba23e2-9431-4f1f-a155-65ddee2e9c7e</xr:TypeId>
				<xr:ValueId>334fe5dd-e211-453c-91d5-cf9f9675284b</xr:ValueId>
			</xr:GeneratedType>
			<xr:GeneratedType name="ConstantValueManager.SupportServiceSoftwareInterfaceAddress" category="ValueManager">
				<xr:TypeId>fd13a0bc-ea7d-4508-a19f-3a7d5bfcb46b</xr:TypeId>
				<xr:ValueId>7f8cddcf-e5e8-4b72-afce-c7e4a25c0621</xr:ValueId>
			</xr:GeneratedType>
		</InternalInfo>
		<Properties>
			<Name>SupportServiceSoftwareInterfaceAddress</Name>
			<Synonym>
				<v8:item>
					<v8:lang>en</v8:lang>
					<v8:content>Address of software interface for support service</v8:content>
				</v8:item>
			</Synonym>
			<Comment/>
			<Type>
				<v8:Type>xs:string</v8:Type>
				<v8:StringQualifiers>
					<v8:Length>0</v8:Length>
					<v8:AllowedLength>Variable</v8:AllowedLength>
				</v8:StringQualifiers>
			</Type>
			<UseStandardCommands>true</UseStandardCommands>
			<DefaultForm/>
			<ExtendedPresentation/>
			<Explanation/>
			<PasswordMode>false</PasswordMode>
			<Format/>
			<EditFormat/>
			<ToolTip/>
			<MarkNegatives>false</MarkNegatives>
			<Mask/>
			<MultiLine>false</MultiLine>
			<ExtendedEdit>false</ExtendedEdit>
			<MinValue xsi:nil="true"/>
			<MaxValue xsi:nil="true"/>
			<FillChecking>DontCheck</FillChecking>
			<ChoiceFoldersAndItems>Items</ChoiceFoldersAndItems>
			<ChoiceParameterLinks/>
			<ChoiceParameters/>
			<QuickChoice>Auto</QuickChoice>
			<ChoiceForm/>
			<LinkByType/>
			<ChoiceHistoryOnInput>Auto</ChoiceHistoryOnInput>
			<DataLockControlMode>Managed</DataLockControlMode>
		</Properties>
	</Constant>
</MetaDataObject>