<?xml version="1.0" encoding="UTF-8"?>
<ExchangePlanContent xmlns="http://v8.1c.ru/8.3/xcf/extrnprops" xmlns:xr="http://v8.1c.ru/8.3/xcf/readable" xmlns:xs="http://www.w3.org/2001/XMLSchema" xmlns:xsi="http://www.w3.org/2001/XMLSchema-instance" version="2.2">
	<Item>
		<Metadata>InformationRegister.IndividualsDocuments</Metadata>
		<AutoRecord>Deny</AutoRecord>
	</Item>
	<Item>
		<Metadata>Document.ProcessingReport</Metadata>
		<AutoRecord>Deny</AutoRecord>
	</Item>
	<Item>
		<Metadata>Document.AcceptanceCertificate</Metadata>
		<AutoRecord>Deny</AutoRecord>
	</Item>
	<Item>
		<Metadata>Document.PaymentReceipt</Metadata>
		<AutoRecord>Deny</AutoRecord>
	</Item>
	<Item>
		<Metadata>InformationRegister.InfobasesObjectsCompliance</Metadata>
		<AutoRecord>Deny</AutoRecord>
	</Item>
	<Item>
		<Metadata>Document.InvoiceForPayment</Metadata>
		<AutoRecord>Deny</AutoRecord>
	</Item>
	<Item>
		<Metadata>Document.PaymentOrder</Metadata>
		<AutoRecord>Deny</AutoRecord>
	</Item>
	<Item>
		<Metadata>Document.CashReceipt</Metadata>
		<AutoRecord>Deny</AutoRecord>
	</Item>
	<Item>
		<Metadata>Catalog.Banks</Metadata>
		<AutoRecord>Deny</AutoRecord>
	</Item>
	<Item>
		<Metadata>Document.AdditionalCosts</Metadata>
		<AutoRecord>Deny</AutoRecord>
	</Item>
	<Item>
		<Metadata>Catalog.BankAccounts</Metadata>
		<AutoRecord>Deny</AutoRecord>
	</Item>
	<Item>
		<Metadata>Catalog.ProductsAndServicesCategories</Metadata>
		<AutoRecord>Deny</AutoRecord>
	</Item>
	<Item>
		<Metadata>Catalog.IndividualsDocumentsKinds</Metadata>
		<AutoRecord>Deny</AutoRecord>
	</Item>
	<Item>
		<Metadata>Document.RetailRevaluation</Metadata>
		<AutoRecord>Deny</AutoRecord>
	</Item>
	<Item>
		<Metadata>Catalog.PriceKinds</Metadata>
		<AutoRecord>Deny</AutoRecord>
	</Item>
	<Item>
		<Metadata>Document.InventoryWriteOff</Metadata>
		<AutoRecord>Deny</AutoRecord>
	</Item>
	<Item>
		<Metadata>Document.CashPayment</Metadata>
		<AutoRecord>Deny</AutoRecord>
	</Item>
	<Item>
		<Metadata>Catalog.Companies</Metadata>
		<AutoRecord>Deny</AutoRecord>
	</Item>
	<Item>
		<Metadata>Document.PaymentExpense</Metadata>
		<AutoRecord>Deny</AutoRecord>
	</Item>
	<Item>
		<Metadata>Document.Netting</Metadata>
		<AutoRecord>Deny</AutoRecord>
	</Item>
	<Item>
		<Metadata>Catalog.ContactInformationTypes</Metadata>
		<AutoRecord>Deny</AutoRecord>
	</Item>
	<Item>
		<Metadata>Document.ExpenseReport</Metadata>
		<AutoRecord>Deny</AutoRecord>
	</Item>
	<Item>
		<Metadata>Document.CustomerOrder</Metadata>
		<AutoRecord>Deny</AutoRecord>
	</Item>
	<Item>
		<Metadata>Document.AgentReport</Metadata>
		<AutoRecord>Deny</AutoRecord>
	</Item>
	<Item>
		<Metadata>Document.RetailReport</Metadata>
		<AutoRecord>Deny</AutoRecord>
	</Item>
	<Item>
		<Metadata>Catalog.Specifications</Metadata>
		<AutoRecord>Deny</AutoRecord>
	</Item>
	<Item>
		<Metadata>Document.SupplierInvoiceNote</Metadata>
		<AutoRecord>Deny</AutoRecord>
	</Item>
	<Item>
		<Metadata>Document.InventoryReconciliation</Metadata>
		<AutoRecord>Deny</AutoRecord>
	</Item>
	<Item>
		<Metadata>Document.CashTransfer</Metadata>
		<AutoRecord>Deny</AutoRecord>
	</Item>
	<Item>
		<Metadata>Document.CustomerInvoiceNote</Metadata>
		<AutoRecord>Deny</AutoRecord>
	</Item>
	<Item>
		<Metadata>Catalog.ProductsAndServices</Metadata>
		<AutoRecord>Deny</AutoRecord>
	</Item>
	<Item>
		<Metadata>Document.SupplierInvoice</Metadata>
		<AutoRecord>Deny</AutoRecord>
	</Item>
	<Item>
		<Metadata>Catalog.CashFlowItems</Metadata>
		<AutoRecord>Deny</AutoRecord>
	</Item>
	<Item>
		<Metadata>Document.InventoryTransfer</Metadata>
		<AutoRecord>Deny</AutoRecord>
	</Item>
	<Item>
		<Metadata>Document.InventoryAssembly</Metadata>
		<AutoRecord>Deny</AutoRecord>
	</Item>
	<Item>
		<Metadata>Document.ReportToPrincipal</Metadata>
		<AutoRecord>Deny</AutoRecord>
	</Item>
	<Item>
		<Metadata>Catalog.WorldCountries</Metadata>
		<AutoRecord>Deny</AutoRecord>
	</Item>
	<Item>
		<Metadata>Catalog.CCDNumbers</Metadata>
		<AutoRecord>Deny</AutoRecord>
	</Item>
	<Item>
		<Metadata>Catalog.Counterparties</Metadata>
		<AutoRecord>Deny</AutoRecord>
	</Item>
	<Item>
		<Metadata>Catalog.AlcoholicProductsVendorLicenses</Metadata>
		<AutoRecord>Deny</AutoRecord>
	</Item>
	<Item>
		<Metadata>Catalog.Currencies</Metadata>
		<AutoRecord>Deny</AutoRecord>
	</Item>
	<Item>
		<Metadata>Document.InventoryReceipt</Metadata>
		<AutoRecord>Deny</AutoRecord>
	</Item>
	<Item>
		<Metadata>Catalog.Individuals</Metadata>
		<AutoRecord>Deny</AutoRecord>
	</Item>
	<Item>
		<Metadata>Document.CustomerInvoice</Metadata>
		<AutoRecord>Deny</AutoRecord>
	</Item>
	<Item>
		<Metadata>InformationRegister.IndividualsDescriptionFull</Metadata>
		<AutoRecord>Deny</AutoRecord>
	</Item>
	<Item>
		<Metadata>Catalog.AlcoholicProductsKinds</Metadata>
		<AutoRecord>Deny</AutoRecord>
	</Item>
	<Item>
		<Metadata>Catalog.StructuralUnits</Metadata>
		<AutoRecord>Deny</AutoRecord>
	</Item>
	<Item>
		<Metadata>Catalog.UOMClassifier</Metadata>
		<AutoRecord>Deny</AutoRecord>
	</Item>
	<Item>
		<Metadata>Document.SubcontractorReport</Metadata>
		<AutoRecord>Deny</AutoRecord>
	</Item>
	<Item>
		<Metadata>Catalog.CounterpartyContracts</Metadata>
		<AutoRecord>Deny</AutoRecord>
	</Item>
</ExchangePlanContent>